nekoweb/__init__.py
nekoweb/nkw_client.py
nekoweb/nkw_constants.py
nekoweb/nkw_core.py
nekoweb/nkw_files/__init__.py
nekoweb/nkw_files/nkw_readfolder.py
nekoweb/nkw_types.py
nekoweb-0.1.1.dist-info/LICENSE
nekoweb-0.1.1.dist-info/METADATA
nekoweb-0.1.1.dist-info/WHEEL
nekoweb-0.1.1.dist-info/RECORD
